kluff/__init__.py
kluff/main.py
kluff/controllers/__init__.py
kluff/controllers/base.py
kluff/controllers/create_apps.py
kluff/core/__init__.py
kluff/core/exc.py
kluff/core/version.py
kluff/ext/__init__.py
kluff/plugins/__init__.py
kluff/templates/__init__.py
kluff/templates/command1.jinja2
kluff/templates/proxySetup.jinja2
kluff/templates/template1.jinja2
kluff/templates/python/Dockerfile
kluff/templates/python/app.py
kluff/templates/python/requirements.txt
kluff/templates/react/Dockerfile
kluff/templates/react/package.json
kluff/templates/react/public/favicon.ico
kluff/templates/react/public/index.html
kluff/templates/react/public/logo192.png
kluff/templates/react/public/logo512.png
kluff/templates/react/public/manifest.json
kluff/templates/react/public/robots.txt
kluff/templates/react/src/App.css
kluff/templates/react/src/App.js
kluff/templates/react/src/App.test.js
kluff/templates/react/src/index.css
kluff/templates/react/src/index.js
kluff/templates/react/src/logo.svg
kluff/templates/react/src/reportWebVitals.js
kluff/templates/react/src/setupTests.js
kluff/utils/__init__.py
kluff/utils/utils.py
kluff-0.0.17.dist-info/LICENSE.md
kluff-0.0.17.dist-info/METADATA
kluff-0.0.17.dist-info/WHEEL
kluff-0.0.17.dist-info/entry_points.txt
kluff-0.0.17.dist-info/top_level.txt
kluff-0.0.17.dist-info/RECORD
