Metadata-Version: 2.1
Name: kluff
Version: 0.0.17
Summary: Build and Deploy with Kluff
Home-page: https://github.com/kluff-com/kluff-cli
Author: Vinay Gode
Author-email: vinay@kluff.com
License: unlicensed
Platform: UNKNOWN
License-File: LICENSE.md
